whatsapp_api/__init__.py
whatsapp_api/whastapp_client.py
whtasapp_wapi-0.0.2.dist-info/LICENSE
whtasapp_wapi-0.0.2.dist-info/METADATA
whtasapp_wapi-0.0.2.dist-info/WHEEL
whtasapp_wapi-0.0.2.dist-info/top_level.txt
whtasapp_wapi-0.0.2.dist-info/RECORD
