Metadata-Version: 2.1
Name: whtasapp-wapi
Version: 0.0.2
Summary: Collection of method to send interactive msg
Home-page: UNKNOWN
Author: Aditya Shukla
Author-email: adityashukla727@gmail.com
License: UNKNOWN
Platform: UNKNOWN
Classifier: Programming Language :: Python :: 3
Classifier: License :: OSI Approved :: MIT License
Classifier: Operating System :: OS Independent
